{
  "executive_summary": "SuperTuxKart is generally well-received, with many users praising its open-source nature, lack of ads, and fun gameplay reminiscent of Mario Kart.  However, a significant portion of negative feedback focuses on control issues, particularly on mobile devices, and some users report performance problems. Suggestions include improving controls, optimizing performance, and adding more content.",
  "problem_analysis": {
    "table": [
      {
        "category": "Controls/Usability Issues",
        "frequency": 45,
        "severity": "Major",
        "example_reviews": [
          {"content": "Controls are very difficult compared to the pc version", "at": "2025-02-02"},
          {"content": "Controls are not helping at all, I'm against the steering wheel type of control and prefer steering with buttons", "at": "2024-12-22"},
          {"content": "Controls are little annoying", "at": "2023-01-29"}
        ],
        "trend": "Stable",
        "affected_user_segments": ["Casual Users", "New Users"]
      },
      {
        "category": "Bugs/Glitches",
        "frequency": 20,
        "severity": "Critical",
        "example_reviews": [
          {"content": "the multi-player is sooo buggy", "at": "2025-01-19"},
          {"content": "it kept saying ( do you want to quit Kart ) and it's annoying me", "at": "2024-11-15"},
          {"content": "Froze at collision, unplayable", "at": "2024-09-14"}
        ],
        "trend": "Increasing",
        "affected_user_segments": ["All Users"]
      },
      {
        "category": "Performance Problems",
        "frequency": 15,
        "severity": "Major",
        "example_reviews": [
          {"content": "Number of kart increasing start lagging", "at": "2023-12-26"},
          {"content": "Lag issue", "at": "2024-07-31"},
          {"content": "bad frame rate", "at": "2023-02-03"}
        ],
        "trend": "Stable",
        "affected_user_segments": ["All Users"]
      },
      {
        "category": "Installation Issues",
        "frequency": 8,
        "severity": "Critical",
        "example_reviews": [
          {"content": "IT Not STATING", "at": "2023-12-09"},
          {"content": "this game cannot download", "at": "2023-06-08"},
          {"content": "I can't install this game!!!!", "at": "2023-05-22"}
        ],
        "trend": "Stable",
        "affected_user_segments": ["New Users"]
      },
      {
        "category": "Feature Issues",
        "frequency": 5,
        "severity": "Minor",
        "example_reviews": [
          {"content": "power up not working", "at": "2024-06-24"},
          {"content": "Need accilater", "at": "2024-03-07"},
          {"content": "Not arrow touch controller also my gamepad doesnt detected", "at": "2023-09-30"}
        ],
        "trend": "Stable",
        "affected_user_segments": ["Power Users"]
      },
      {
        "category": "Content/Quality Issues",
        "frequency": 3,
        "severity": "Minor",
        "example_reviews": [
          {"content": "sound effects are kinda bad", "at": "2023-12-31"},
          {"content": "soo bad graphics and sound", "at": "2023-10-15"},
          {"content": "Kart classes are lacking a little, though", "at": "2024-09-29"}
        ],
        "trend": "Stable",
        "affected_user_segments": ["All Users"]
      }
    ],
    "trend_summary": "The 'Do you want to quit' bug is a recurring issue. Control problems are consistently mentioned. Performance issues are also a concern.",
    "critical_problems_count": 2,
    "most_affected_segments": ["New Users"]
  },
  "suggestion_analysis": {
    "table": [
      {
        "suggestion_group": "Improved Controls",
        "frequency": 30,
        "estimated_impact": "High",
        "implementation_difficulty": "Medium",
        "example_reviews": [
          {"content": "But a driving game should have an option for a driver point of view."},
          {"content": "Controls are very difficult compared to the pc version"},
          {"content": "I love the game however kindly asking if the controls can be made a little easy like in beach buggy racing"}
        ]
      },
      {
        "suggestion_group": "Graphics Optimization",
        "frequency": 15,
        "estimated_impact": "Medium",
        "implementation_difficulty": "Medium",
        "example_reviews": [
          {"content": "U NEED TO UPGRADE THE GRAPHICS OF GAME"},
          {"content": "Increase the game size and improve the graphics"}
        ]
      },
      {
        "suggestion_group": "More Content (Tracks/Characters)",
        "frequency": 10,
        "estimated_impact": "Medium",
        "implementation_difficulty": "Medium",
        "example_reviews": [
          {"content": "Very good game but add some mape and mode"},
          {"content": "add a game mode called capture the flag pleeease"}
        ]
      },
      {
        "suggestion_group": "Fix 'Do you want to quit' Bug",
        "frequency": 8,
        "estimated_impact": "High",
        "implementation_difficulty": "Easy",
        "example_reviews": [
          {"content": "it says do you wanna quit and it's annoying >:("},
          {"content": "it keeps saying do you want to quit STK worst game ever"}
        ]
      }
    ],
    "emerging_suggestions": "No significant emerging suggestions were identified in the later reviews.",
    "high_impact_count": 2,
    "quick_wins": ["Fix the 'Do you want to quit' bug as it's a high-impact, low-difficulty issue."]
  },
  "sentiment_trend_analysis": {
    "summary": "Overall sentiment is positive, but negative sentiment spikes are associated with bug reports and control issues.  The 'Do you want to quit' bug consistently generates negative feedback.",
    "period_trends": [
      {"period": "2024 Q4", "positive_percentage": 65, "negative_percentage": 20, "neutral_percentage": 15},
      {"period": "2025 Q1", "positive_percentage": 70, "negative_percentage": 15, "neutral_percentage": 15},
      {"period": "2025 Q2", "positive_percentage": 75, "negative_percentage": 10, "neutral_percentage": 15}
    ],
    "significant_events": [
      {"date": "2024-12-22", "event": "Reports of controller issues", "sentiment_impact": "Negative"}
    ]
  },
  "user_segments": {
    "identified_segments": ["Power Users", "Casual Users", "New Users"],
    "segment_specific_issues": [
      {"segment": "New Users", "top_issues": ["Installation Problems", "Difficult Controls"]}
    ]
  },
  "actionable_insights": [
    "Prioritize fixing the 'Do you want to quit' bug due to its high frequency and negative impact.",
    "Implement alternative control schemes (e.g., button-based) to improve usability on mobile devices.",
    "Investigate and address performance bottlenecks to ensure smooth gameplay on a wider range of devices."
  ]
}